trenalyze__python/__init__.py
trenalyze_python-0.0.2.dist-info/LICENSE
trenalyze_python-0.0.2.dist-info/METADATA
trenalyze_python-0.0.2.dist-info/WHEEL
trenalyze_python-0.0.2.dist-info/top_level.txt
trenalyze_python-0.0.2.dist-info/RECORD
