Metadata-Version: 2.1
Name: trenalyze-python
Version: 0.0.2
Summary: A Python package to send WhatsApp messages through Trenalyze
Home-page: https://github.com/Trenalyze/trenalyze__python
Author: Treasure Uvietobore
Author-email: uvietoboretreasure@gmail.com
License: MIT
Platform: UNKNOWN
Requires-Python: >=3.6
License-File: LICENSE
Requires-Dist: requests
